datalint_core-0.1.1.dist-info/METADATA
datalint_core-0.1.1.dist-info/WHEEL
datalint_core-0.1.1.dist-info/licenses/LICENSE
datalint_core/__init__.py
datalint_core/_datalint_core.cpython-39-darwin.so
datalint_core/_datalint_core.pyi
datalint_core/py.typed
datalint_core-0.1.1.dist-info/RECORD
