Metadata-Version: 2.4
Name: datalint-core
Version: 0.1.1
Classifier: Programming Language :: Rust
Classifier: Programming Language :: Python :: Implementation :: CPython
Classifier: Programming Language :: Python :: Implementation :: PyPy
License-File: LICENSE
License: Apache-2.0
Requires-Python: >=3.9
